[
  {"source_id":"cnpc-careers","name":"中国石油高校毕业生招聘平台","url":"https://zhaopin.cnpc.com.cn/","source_type":"集团招聘平台","trust":"official","unit_ids":["cnpc"],"mode":"html","official_domains":["zhaopin.cnpc.com.cn","cnpc.com.cn"]},
  {"source_id":"sinopec-careers","name":"中国石化招聘网站","url":"https://job.sinopec.com/","source_type":"集团招聘平台","trust":"official","unit_ids":["sinopec"],"mode":"html","official_domains":["job.sinopec.com","sinopec.com","sinopecgroup.com"]},
  {"source_id":"cnooc-careers","name":"中国海油校园招聘","url":"https://cnooc.zhaopin.com/","source_type":"集团招聘平台","trust":"official","unit_ids":["cnooc"],"mode":"html","official_domains":["cnooc.zhaopin.com","cnooc.com.cn"]},
  {"source_id":"cnooc-iguopin","name":"中国海油国聘招聘页","url":"https://cnooc.iguopin.com/job","source_type":"权威招聘平台","trust":"authoritative","unit_ids":["cnooc"],"mode":"html","official_domains":["cnooc.iguopin.com","iguopin.com"]},
  {"source_id":"chn-energy-careers","name":"国家能源集团人力资源招聘网站","url":"https://zhaopin.chnenergy.com.cn/recTypeSerch?kinds=1","source_type":"集团招聘平台","trust":"official","unit_ids":["chn-energy"],"mode":"html","official_domains":["zhaopin.chnenergy.com.cn","chnenergy.com.cn"]},
  {"source_id":"chinacoal-careers","name":"中国中煤招聘网站","url":"https://zhaopin.chinacoal.com/","source_type":"集团招聘平台","trust":"official","unit_ids":["chinacoal"],"mode":"html","official_domains":["zhaopin.chinacoal.com","chinacoal.com"]},
  {"source_id":"chinacoal-notices","name":"中国中煤通知公告","url":"https://www.chinacoal.com/col/col37/index.html","source_type":"集团官网公告","trust":"official","unit_ids":["chinacoal"],"mode":"html","official_domains":["chinacoal.com"]},
  {"source_id":"ccgc-careers","name":"中国煤炭地质总局人才招聘","url":"https://www.ccgc.cn/?mod=zhaopin&tid=129","source_type":"总局招聘公告","trust":"official","unit_ids":["ccgc"],"mode":"html","official_domains":["ccgc.cn"]},
  {"source_id":"ccgc-research","name":"中国煤炭地质总局勘查研究总院","url":"https://kczy.ccgc.cn/","source_type":"直属单位官网","trust":"official","unit_ids":["ccgc","ccgc-research-institute"],"mode":"html","official_domains":["kczy.ccgc.cn","ccgc.cn"]},
  {"source_id":"cmgb-careers","name":"中国冶金地质总局招聘信息","url":"https://www.cmgb.com.cn/category/zpxx.html","source_type":"总局招聘公告","trust":"official","unit_ids":["cmgb"],"mode":"html","official_domains":["cmgb.com.cn"]},
  {"source_id":"cmgb-first-careers","name":"国冶一局招聘信息","url":"https://www.zykyj.com/zykyj/879977/938535/index.html","source_type":"直属单位官网","trust":"official","unit_ids":["cmgb-first"],"mode":"html","official_domains":["zykyj.com"]},
  {"source_id":"ccgmb-careers","name":"中化地质矿山总局人员招聘","url":"https://www.ccgmb.com/news/16.html","source_type":"总局招聘公告","trust":"official","unit_ids":["ccgmb"],"mode":"html","official_domains":["ccgmb.com"]},
  {"source_id":"ccgmb-research","name":"中化地质矿山总局地质研究院","url":"https://www.hgdyy.com.cn/","source_type":"直属单位官网","trust":"official","unit_ids":["ccgmb-research"],"mode":"html","official_domains":["hgdyy.com.cn"]},
  {"source_id":"ccgmb-zhejiang","name":"中化浙江地质勘查院","url":"https://www.zjccgmb.com/","source_type":"直属单位官网","trust":"official","unit_ids":["ccgmb-zhejiang"],"mode":"html","official_domains":["zjccgmb.com"]},
  {"source_id":"ccgmb-hubei","name":"中化湖北地质勘查院","url":"https://www.zhhby1.cn/","source_type":"直属单位官网","trust":"official","unit_ids":["ccgmb-hubei"],"mode":"html","official_domains":["zhhby1.cn"]},
  {"source_id":"ccgmb-hunan","name":"中化湖南地质勘查院","url":"https://www.zhhny.com/","source_type":"直属单位官网","trust":"official","unit_ids":["ccgmb-hunan"],"mode":"html","official_domains":["zhhny.com"]},
  {"source_id":"minmetals-careers","name":"中国五矿招聘官网","url":"https://minmetals.hotjob.cn/","source_type":"集团招聘平台","trust":"official","unit_ids":["minmetals"],"mode":"html","official_domains":["minmetals.hotjob.cn","minmetals.com.cn"]},
  {"source_id":"minmetals-nonferrous","name":"五矿有色人才招聘","url":"https://cmnltd.minmetals.com.cn/rczp/","source_type":"子公司官网","trust":"official","unit_ids":["minmetals-nonferrous"],"mode":"html","official_domains":["cmnltd.minmetals.com.cn","minmetals.com.cn"]},
  {"source_id":"china-gold-careers","name":"中国黄金集团招聘平台","url":"https://hjzp.chinagoldgroup.com/recruit","source_type":"集团招聘平台","trust":"official","unit_ids":["china-gold"],"mode":"html","official_domains":["hjzp.chinagoldgroup.com","chinagoldgroup.com"]},
  {"source_id":"china-gold-notices","name":"中国黄金集团人才招聘","url":"https://www.chinagoldgroup.com/zghj/rlzy/zczp/A080008001Gone1.html","source_type":"集团官网公告","trust":"official","unit_ids":["china-gold"],"mode":"html","official_domains":["chinagoldgroup.com"]},
  {"source_id":"chinalco-careers","name":"中国铝业集团国聘平台","url":"https://chinalco.iguopin.com/notice","source_type":"集团招聘平台","trust":"authoritative","unit_ids":["chinalco","yunnan-copper"],"mode":"html","official_domains":["chinalco.iguopin.com","iguopin.com"]},
  {"source_id":"chinalco-notices","name":"中国铝业集团人力资源","url":"https://www.chinalco.com.cn/rlzy/","source_type":"集团官网公告","trust":"official","unit_ids":["chinalco"],"mode":"restricted","official_domains":["chinalco.com.cn"]},
  {"source_id":"cnmc-careers","name":"中国有色矿业集团官网（含人才招聘入口）","url":"https://www.cnmc.com.cn/","source_type":"集团官网公告","trust":"official","unit_ids":["cnmc"],"mode":"html","official_domains":["cnmc.com.cn"]},
  {"source_id":"pipechina-careers","name":"国家管网集团招聘平台","url":"https://zhaopin.pipechina.com.cn/","source_type":"集团招聘平台","trust":"official","unit_ids":["pipechina"],"mode":"html","official_domains":["zhaopin.pipechina.com.cn","pipechina.com.cn"]},
  {"source_id":"shandong-energy-careers","name":"山东能源集团招聘网站","url":"https://zhaopin.shandong-energy.com/recruit","source_type":"集团招聘平台","trust":"official","unit_ids":["shandong-energy"],"mode":"html","official_domains":["zhaopin.shandong-energy.com","shandong-energy.com"]},
  {"source_id":"shccig-careers","name":"陕煤集团人才招聘网","url":"https://webhr.shccig.com/webhrN2-zp/home","source_type":"集团招聘平台","trust":"official","unit_ids":["shccig"],"mode":"html","official_domains":["webhr.shccig.com","shccig.com"]},
  {"source_id":"jinneng-notices","name":"晋能控股通知公告","url":"https://www.jnkgjtnews.com/tzgg.htm","source_type":"集团官网公告","trust":"official","unit_ids":["jinneng"],"mode":"html","official_domains":["jnkgjtnews.com"]},
  {"source_id":"shanxi-coking-notices","name":"山西焦煤通知公告","url":"https://www.sxcc.com.cn/tzgg/","source_type":"集团官网公告","trust":"official","unit_ids":["shanxi-coking"],"mode":"html","official_domains":["sxcc.com.cn"]},
  {"source_id":"huaihe-energy-home","name":"淮河能源集团官网","url":"https://www.hhnyjt.com/","source_type":"集团官网","trust":"official","unit_ids":["huaihe-energy"],"mode":"html","official_domains":["hhnyjt.com"]},
  {"source_id":"jizhong-energy-home","name":"冀中能源集团官网","url":"https://www.jznyjt.com/","source_type":"集团官网","trust":"official","unit_ids":["jizhong-energy"],"mode":"html","official_domains":["jznyjt.com"]},
  {"source_id":"kailuan-home","name":"开滦集团官网","url":"https://www.kailuan.com.cn/","source_type":"集团官网","trust":"official","unit_ids":["kailuan"],"mode":"html","official_domains":["kailuan.com.cn"]},
  {"source_id":"henan-energy-home","name":"河南能源集团官网","url":"https://www.hnecgc.com.cn/","source_type":"集团官网","trust":"official","unit_ids":["henan-energy"],"mode":"html","official_domains":["hnecgc.com.cn"]},
  {"source_id":"longmay-home","name":"龙煤集团官网","url":"https://www.longmay.com.cn/","source_type":"集团官网","trust":"official","unit_ids":["longmay"],"mode":"html","official_domains":["longmay.com.cn"]},
  {"source_id":"shandong-gold-home","name":"山东黄金集团官网","url":"https://www.sd-gold.com/","source_type":"集团官网","trust":"official","unit_ids":["shandong-gold"],"mode":"html","official_domains":["sd-gold.com"]},
  {"source_id":"jiangxi-copper-home","name":"江西铜业集团官网","url":"https://www.jxcc.com/","source_type":"集团官网","trust":"official","unit_ids":["jiangxi-copper"],"mode":"html","official_domains":["jxcc.com"]},
  {"source_id":"yunnan-tin-home","name":"云锡集团官网","url":"https://www.ytc.cn/","source_type":"集团官网","trust":"official","unit_ids":["yunnan-tin"],"mode":"html","official_domains":["ytc.cn"]},
  {"source_id":"baogang-home","name":"包钢集团官网","url":"https://www.btsteel.com/","source_type":"集团官网","trust":"official","unit_ids":["baogang"],"mode":"html","official_domains":["btsteel.com"]},
  {"source_id":"northern-rare-earth-home","name":"北方稀土官网","url":"https://www.reht.com/","source_type":"集团官网","trust":"official","unit_ids":["baogang"],"mode":"html","official_domains":["reht.com"]},
  {"source_id":"ansteel-home","name":"鞍钢集团官网","url":"https://www.ansteelgroup.com/","source_type":"集团官网","trust":"official","unit_ids":["steel-mining"],"mode":"html","official_domains":["ansteelgroup.com"]},
  {"source_id":"shougang-home","name":"首钢集团官网","url":"https://www.shougang.com.cn/","source_type":"集团官网","trust":"official","unit_ids":["steel-mining"],"mode":"html","official_domains":["shougang.com.cn"]},
  {"source_id":"hbisco-home","name":"河钢集团官网","url":"https://www.hbisco.com/","source_type":"集团官网","trust":"official","unit_ids":["steel-mining"],"mode":"html","official_domains":["hbisco.com"]},
  {"source_id":"jiugang-home","name":"酒钢集团官网","url":"https://www.jiugang.com/","source_type":"集团官网","trust":"official","unit_ids":["jiugang"],"mode":"html","official_domains":["jiugang.com"]},
  {"source_id":"zhaojin-home","name":"招金集团官网","url":"https://www.zhaojin.com.cn/","source_type":"集团官网","trust":"official","unit_ids":["zhaojin"],"mode":"html","official_domains":["zhaojin.com.cn"]},
  {"source_id":"powerchina-careers","name":"中国电建人才招聘","url":"https://www.powerchina.cn/col/col7436/index.html","source_type":"集团官网公告","trust":"official","unit_ids":["powerchina"],"mode":"html","official_domains":["powerchina.cn"]},
  {"source_id":"energy-china-careers","name":"中国能建校园招聘","url":"https://ceec.iguopin.com/job","source_type":"集团招聘平台","trust":"authoritative","unit_ids":["energy-china"],"mode":"html","official_domains":["ceec.iguopin.com","iguopin.com"]},
  {"source_id":"crec-careers","name":"中国中铁全球人才招引平台","url":"https://zhr.crec.cn/zhaopin/","source_type":"集团招聘平台","trust":"official","unit_ids":["crec"],"mode":"html","official_domains":["zhr.crec.cn","crec.cn"]},
  {"source_id":"crcc-careers","name":"中国铁建招聘平台","url":"https://crcc.hotjob.cn/","source_type":"集团招聘平台","trust":"official","unit_ids":["crcc"],"mode":"html","official_domains":["crcc.hotjob.cn","crcc.cn"]},
  {"source_id":"cccc-careers","name":"中国交建招聘平台","url":"https://zhaopin.ccccltd.cn/","source_type":"集团招聘平台","trust":"official","unit_ids":["cccc"],"mode":"html","official_domains":["zhaopin.ccccltd.cn","ccccltd.cn"]},
  {"source_id":"cscec-careers","name":"中国建筑校园招聘","url":"https://job.cscec.com/","source_type":"集团招聘平台","trust":"official","unit_ids":["cscec"],"mode":"html","official_domains":["job.cscec.com","cscec.com"]},
  {"source_id":"china-aneng-home","name":"中国安能集团官网","url":"https://www.china-an.cn/","source_type":"集团官网","trust":"official","unit_ids":["china-aneng"],"mode":"html","official_domains":["china-an.cn"]},
  {"source_id":"cgs-recruitment","name":"中国地质调查局招聘信息","url":"https://www.cgs.gov.cn/tzgg/zpxx/","source_type":"事业单位招聘公告","trust":"official","unit_ids":["cgs"],"mode":"html","official_domains":["cgs.gov.cn"]},
  {"source_id":"sasac-recruitment","name":"国务院国资委招聘专栏","url":"https://www.sasac.gov.cn/n2588035/n2588325/n2588350/index.html","source_type":"权威招聘平台","trust":"authoritative","unit_ids":[],"mode":"html","official_domains":["sasac.gov.cn"],"tier":"l2","role":"discovery","follow_domains":["sasac.gov.cn","mp.weixin.qq.com"]},
  {"source_id":"iguopin","name":"国聘","url":"https://www.iguopin.com/","source_type":"权威招聘平台","trust":"authoritative","unit_ids":[],"mode":"html","official_domains":["iguopin.com"],"tier":"l2","role":"discovery","follow_domains":["iguopin.com","mp.weixin.qq.com"]},
  {"source_id":"ncss","name":"国家大学生就业服务平台","url":"https://www.ncss.cn/student/jobs/index.html","source_type":"权威招聘平台","trust":"authoritative","unit_ids":[],"mode":"html","official_domains":["ncss.cn"],"tier":"l2","role":"discovery","follow_domains":["ncss.cn","mp.weixin.qq.com"]},
  {"source_id":"mohrss-central-jobs","name":"人社部中央企业招聘应届高校毕业生信息公开","url":"https://job.mohrss.gov.cn/qyzp/index.jhtml","source_type":"人社部权威平台","trust":"authoritative","unit_ids":["cnpc","ccgc","ccgc-research-institute","cmgb-first","ccgmb-research","ccgmb-hunan","crcc","cscec","china-aneng","chinalco"],"mode":"html","official_domains":["job.mohrss.gov.cn","mohrss.gov.cn"],"tier":"l2","role":"discovery","follow_domains":["job.mohrss.gov.cn","mohrss.gov.cn","mp.weixin.qq.com"],"query_terms":["2027届","地质学","地质工程","资源勘查"]},
  {"source_id":"sasac-mobile-jobs","name":"国务院国资委移动端招聘专栏","url":"https://wap.sasac.gov.cn/n2588035/n2588325/n2588350/index.html","source_type":"国务院国资委招聘专栏","trust":"authoritative","unit_ids":["cnpc","ccgc","ccgc-research-institute","cmgb-first","ccgmb-research","ccgmb-hunan","crcc","cscec","china-aneng","chinalco"],"mode":"html","official_domains":["wap.sasac.gov.cn","sasac.gov.cn"],"tier":"l2","role":"discovery","follow_domains":["wap.sasac.gov.cn","sasac.gov.cn","mp.weixin.qq.com"],"query_terms":["2027届","高校毕业生","地质"]},
  {"source_id":"sasac-iguopin-jobs","name":"国资央企招聘平台","url":"https://cujiuye.iguopin.com/","source_type":"国资央企权威平台","trust":"authoritative","unit_ids":["cnpc","sinopec","cnooc","chn-energy","chinacoal","ccgc","ccgc-research-institute","cmgb","cmgb-first","ccgmb","ccgmb-research","ccgmb-hunan","minmetals","china-gold","chinalco","cnmc","pipechina","shandong-energy","shccig","jinneng","shanxi-coking","huaihe-energy","jizhong-energy","kailuan","henan-energy","longmay","shandong-gold","jiangxi-copper","yunnan-copper","yunnan-tin","baogang","steel-mining","jiugang","zhaojin","powerchina","energy-china","crec","crcc","cccc","cscec","china-aneng","cgs"],"mode":"iguopin-api","official_domains":["cujiuye.iguopin.com","iguopin.com"],"tier":"l2","role":"discovery","follow_domains":["cujiuye.iguopin.com","iguopin.com","mp.weixin.qq.com"],"query_terms":["2027届","地质学","地质工程","资源勘查","勘查技术","工程地质","物探","矿山地质"]},
  {"source_id":"shaanxi-sasac-jobs","name":"陕西省国资委招聘栏目","url":"https://sxgz.shaanxi.gov.cn/zfxxgk/fdzdgk/rsxx/zp/","source_type":"省级国资委招聘栏目","trust":"authoritative","unit_ids":["shccig"],"mode":"html","official_domains":["sxgz.shaanxi.gov.cn"],"tier":"l2","role":"discovery","follow_domains":["sxgz.shaanxi.gov.cn","mp.weixin.qq.com"],"query_terms":["陕煤","2027届","地质"]},
  {"source_id":"shanxi-sasac-jobs","name":"山西国资网国企招聘","url":"https://gzw.shanxi.gov.cn/xwfb/gqzp/index.shtml","source_type":"省级国资委招聘栏目","trust":"authoritative","unit_ids":["jinneng","shanxi-coking"],"mode":"html","official_domains":["gzw.shanxi.gov.cn"],"tier":"l2","role":"discovery","follow_domains":["gzw.shanxi.gov.cn","mp.weixin.qq.com"],"query_terms":["山西焦煤","晋能控股","2027届","地质"]},
  {"source_id":"anhui-sasac-jobs","name":"安徽省国资委企业招聘","url":"https://gzw.ah.gov.cn/ssqy/qyzp/index.html","source_type":"省级国资委招聘栏目","trust":"authoritative","unit_ids":["huaihe-energy"],"mode":"html","official_domains":["gzw.ah.gov.cn"],"tier":"l2","role":"discovery","follow_domains":["gzw.ah.gov.cn","mp.weixin.qq.com"],"query_terms":["淮河能源","2027届","地质"]},
  {"source_id":"hebei-sasac-jobs","name":"河北省国资委通知公告","url":"https://hbsa.hebei.gov.cn/TZGG197/index.html","source_type":"省级国资委招聘栏目","trust":"authoritative","unit_ids":["jizhong-energy"],"mode":"html","official_domains":["hbsa.hebei.gov.cn"],"tier":"l2","role":"discovery","follow_domains":["hbsa.hebei.gov.cn","mp.weixin.qq.com"],"query_terms":["冀中能源","2027届","地质"]}
]
